[
  {
    "restaurantName": "外婆家",
    "restaurantPic": "https://img.meituan.net/msmerchant/baabfa65fc58c22881cfe719b9af6ce350179.jpg%40340w_255h_1e_1c_1l%7Cwatermark%3D1%26%26r%3D1%26p%3D9%26x%3D2%26y%3D2%26relative%3D1%26o%3D20",
    "restaurantType": "江浙菜",
    "restaurantPosition": "东城区王府井大街138号",
    "dateNumber": "1880",
    "restaurantId":1
  },
  {
    "restaurantName":"安迪家",
    "restaurantPic": "https://img.meituan.net/msmerchant/508dc5b5f0e0b9e35ab63786e8d990d2320876.jpg%40340w_255h_1e_1c_1l%7Cwatermark%3D1%26%26r%3D1%26p%3D9%26x%3D2%26y%3D2%26relative%3D1%26o%3D20",
    "restaurantType":"西餐",
    "restaurantPosition":"百子湾东里405号楼1-09",
    "dateNumber":"1299",
    "restaurantId":2
  },
  {
    "restaurantName":"海底捞",
    "restaurantPic":"https://img.meituan.net/msmerchant/c4cef6726ae9ae0de91355765d56495e181500.jpg%40340w_255h_1e_1c_1l%7Cwatermark%3D1%26%26r%3D1%26p%3D9%26x%3D2%26y%3D2%26relative%3D1%26o%3D20",
    "restaurantType":"火锅",
    "restaurantPosition":"大兴区亦庄经济开发区",
    "dateNumber":"2399",
    "restaurantId":3
  },
  {
    "restaurantName":"淮阳府",
    "restaurantPic":"http://qcloud.dpfile.com/pc/woJnL9wk6mx488oSeoRyHluBqe7E9O0XQNsqCb1yCUEs4zkFWsiNVa9utiDliPcGs9bU8u7TlyVW3ovyQ7Jtmw.jpg",
    "restaurantType":"江浙菜",
    "restaurantPosition":"安定门外大街",
    "dateNumber":"2392",
    "restaurantId":4
  },
  {
    "restaurantName":"牛串门串串香",
    "restaurantPic": "https://img.meituan.net/msmerchant/013be96ab9e0e8673570909758916cb5135604.jpg%40340w_255h_1e_1c_1l%7Cwatermark%3D1%26%26r%3D1%26p%3D9%26x%3D2%26y%3D2%26relative%3D1%26o%3D20",
    "restaurantType":"火锅",
    "restaurantPosition":"东直门 东直门内大街",
    "dateNumber":"909",
    "restaurantId":5
  },
  {
    "restaurantName":"The View",
    "restaurantPic": "https://img.meituan.net/msmerchant/f991e5f879aaec131f63cd2ee2a78cec32012.jpg%40340w_255h_1e_1c_1l%7Cwatermark%3D1%26%26r%3D1%26p%3D9%26x%3D2%26y%3D2%26relative%3D1%26o%3D20",
    "restaurantType":"西餐",
    "restaurantPosition":"大望路 建国路88号",
    "dateNumber":"2394",
    "restaurantId":6
  },
  {
    "restaurantName":"香浙汇",
    "restaurantPic":"http://p1.meituan.net/mogu/5ef3b65289906eef737705b52f3de660270036.jpg%40340w_255h_1e_1c_1l%7Cwatermark%3D1%26%26r%3D1%26p%3D9%26x%3D2%26y%3D2%26relative%3D1%26o%3D20",
    "restaurantType":"江浙菜",
    "restaurantPosition":"朝阳区望京阜通大街",
    "dateNumber":"1899",
    "restaurantId":7
  },
  {
    "restaurantName":"兰溪小馆",
    "restaurantPic": "https://img.meituan.net/msmerchant/9eeb5e69f35255d8b47193641fba9824382579.png%40340w_255h_1e_1c_1l%7Cwatermark%3D1%26%26r%3D1%26p%3D9%26x%3D2%26y%3D2%26relative%3D1%26o%3D20",
    "restaurantType":"江浙菜",
    "restaurantPosition":"来广营西路诚盈中心1号楼2层",
    "dateNumber":"899",
    "restaurantId":8
  },
  {
    "restaurantName": "大堂茶座",
    "restaurantPic": "https://img.meituan.net/msmerchant/0d804b3dbac1bbf781c4ffb48bfe87774782010.jpg%40340w_255h_1e_1c_1l%7Cwatermark%3D1%26%26r%3D1%26p%3D9%26x%3D2%26y%3D2%26relative%3D1%26o%3D20",
    "restaurantType": "下午茶",
    "restaurantPosition": "王府井/东单 金鱼胡同8号王府半岛酒店1楼",
    "dateNumber": "416",
    "restaurantId":9
  },
  {
    "restaurantName": "梧桐咖啡",
    "restaurantPic": "https://img.meituan.net/msmerchant/b10da7b2921048d3890443615b953a7a303607.jpg%40340w_255h_1e_1c_1l%7Cwatermark%3D1%26%26r%3D1%26p%3D9%26x%3D2%26y%3D2%26relative%3D1%26o%3D20",
    "restaurantType": "下午茶",
    "restaurantPosition": "三里屯 工体北路8号院三里屯SOHO1号商场B1层122号",
    "dateNumber": "873",
    "restaurantId":10
  }
]
